divissr/__init__.py
divissr/core.py
divissr/fastq_gzip_reader.h
divissr/fastq_reader.h
divissr/utils.h
divissr/lib/4097_figure1_v2.jpg
divissr/lib/divissr_fasta_template.html
divissr/lib/divissr_fastq_template.html
divissr/lib/src/all.js
divissr/lib/src/anno_charts.js
divissr/lib/src/echarts.min.js
divissr/lib/src/echarts_cp1252.min.js
divissr/lib/src/jquery-3.5.0.min.js
divissr/lib/src/jquery.multi-select.min.js
divissr/lib/src/main_fasta.js
divissr/lib/src/main_fastq.js
divissr/lib/src/tables_fasta.js
divissr/lib/src/tables_fastq.js
divissr/lib/src/test.js
divissr/lib/styles/main.css
divissr/lib/styles/multi-select.min.css
divissr/templates/pydivissr_fasta_gzip_template.cpp
divissr/templates/pydivissr_fasta_template.cpp
divissr/templates/pydivissr_fastq_gzip_template.cpp
divissr/templates/pydivissr_fastq_template.cpp
divissr/utils/__init__.py
divissr/utils/analyse.py
divissr/utils/annotation.py
divissr/utils/seq_utils.py
divissr-0.1.2.dist-info/LICENSE
divissr-0.1.2.dist-info/METADATA
divissr-0.1.2.dist-info/WHEEL
divissr-0.1.2.dist-info/entry_points.txt
divissr-0.1.2.dist-info/top_level.txt
divissr-0.1.2.dist-info/RECORD
