Metadata-Version: 2.1
Name: divissr
Version: 0.1.2
Summary: DiviSSR is a DNA tandem repeat identification tool
Home-page: https://github.com/avvaruakshay/divissr.git
Author: Akshay Avvaru
Author-email: avvaru@ccmb.res.in
License: UNKNOWN
Project-URL: Bug Tracker, https://github.com/avvaruakshay/divissr/issues
Platform: UNKNOWN
Classifier: Programming Language :: Python :: 3
Classifier: License :: OSI Approved :: MIT License
Classifier: Operating System :: OS Independent
License-File: LICENSE
